pylabdd/PK_force.f90
pylabdd/__init__.py
pylabdd/dislocations.py
pylabdd/PK_force/PK_force.f90
pylabdd/PK_force/PK_force.x86_64.so
pylabdd/PK_force/PK_force_c_wrapper.f90
pylabdd/PK_force/PK_force_python_wrapper.py
pylabdd/PK_force/__init__.py
pylabdd/PK_force/__pycache__/__init__.cpython-310.pyc
pylabdd/PK_force_py/__init__.py
pylabdd/PK_force_py/pkforce.py
pylabdd/buildtools/__init__.py
pylabdd/buildtools/setup_fortran.py
pylabdd-1.2.5.dist-info/licenses/LICENSE
pylabdd-1.2.5.dist-info/METADATA
pylabdd-1.2.5.dist-info/WHEEL
pylabdd-1.2.5.dist-info/top_level.txt
pylabdd-1.2.5.dist-info/RECORD
