Metadata-Version: 2.4
Name: pylabdd
Version: 1.2.5
Summary: Python Laboratory for Dislocation Dynamics
Author-email: Alexander Hartmaier <alexander.hartmaier@rub.de>
License-Expression: GPL-3.0-or-later
Project-URL: Homepage, https://github.com/AHartmaier/pyLabDD
Classifier: Development Status :: 4 - Beta
Classifier: Intended Audience :: Science/Research
Classifier: Natural Language :: English
Classifier: Programming Language :: Python :: 3.10
Classifier: Programming Language :: Python :: 3.11
Classifier: Programming Language :: Python :: 3.12
Classifier: Programming Language :: Python :: 3.13
Classifier: Topic :: Scientific/Engineering :: Physics
Requires-Python: >=3.10
License-File: LICENSE
Requires-Dist: numpy
Requires-Dist: matplotlib
Requires-Dist: fmodpy
Provides-Extra: dev
Requires-Dist: pytest; extra == "dev"
Requires-Dist: black; extra == "dev"
Requires-Dist: build; extra == "dev"
Requires-Dist: twine; extra == "dev"
Dynamic: license-file
